MANIFEST.in
Makefile
README
setup.py
markdown_checklist_nd/__init__.py
markdown_checklist_nd/extension.py
markdown_checklist_nodisable.egg-info/PKG-INFO
markdown_checklist_nodisable.egg-info/SOURCES.txt
markdown_checklist_nodisable.egg-info/dependency_links.txt
markdown_checklist_nodisable.egg-info/not-zip-safe
markdown_checklist_nodisable.egg-info/requires.txt
markdown_checklist_nodisable.egg-info/top_level.txt
test/__init__.py
test/test_main.py