Metadata-Version: 1.0
Name: markdown-checklist-nodisable
Version: 0.4.3
Summary: Python Markdown extension for task lists with checkboxes
Home-page: https://github.com/jstacoder/markdown-checklist
Author: FND
Author-email: UNKNOWN
License: MIT
Platform: Posix; MacOS X; Windows
